fred_pandas/__init__.py
fred_pandas/fred_pandas.py
fred_pandas-0.0.3.dist-info/METADATA
fred_pandas-0.0.3.dist-info/WHEEL
fred_pandas-0.0.3.dist-info/licenses/LICENSE
fred_pandas-0.0.3.dist-info/RECORD
